{
  "toc": [
    {
      "uri": "lynx1_general_overview",
      "title": "Chapter 1: General Overview",
      "description": "Marketing Feature Set and External Specification",
      "mimeType": "text/markdown"
    },
    {
      "uri": "lynx2_hardware_overview",
      "title": "Chapter 2: Hardware Overview",
      "description": "System components overview including CPU, Mikey, and Suzy",
      "mimeType": "text/markdown"
    },
    {
      "uri": "lynx3_software_hardware_perniciousness",
      "title": "Chapter 3: Software Related Hardware Perniciousness",
      "description": "Important notes about hardware quirks and issues",
      "mimeType": "text/markdown"
    },
    {
      "uri": "lynx4_cpu_rom",
      "title": "Chapter 4-5: CPU/ROM",
      "description": "CPU cycle timing, ROM, and CPU Sleep documentation",
      "mimeType": "text/markdown"
    },
    {
      "uri": "lynx5_display",
      "title": "Chapter 6: Display",
      "description": "Frame Rate, Pen Numbers/Color Palette, Display Buffers",
      "mimeType": "text/markdown"
    },
    {
      "uri": "lynx6_sprite_collision",
      "title": "Chapter 7: Sprite/Collision",
      "description": "Sprite features, data structure, and engine documentation",
      "mimeType": "text/markdown"
    },
    {
      "uri": "lynx7_audio_tape_romcart",
      "title": "Chapter 8-10: Audio, Magnetic Tape, ROM Cart",
      "description": "Audio system, magnetic tape interface, and ROM cartridge",
      "mimeType": "text/markdown"
    },
    {
      "uri": "lynx8_timers_interrupts",
      "title": "Chapter 11: Timers/Interrupts",
      "description": "Timer system and interrupt handling",
      "mimeType": "text/markdown"
    },
    {
      "uri": "lynx8a_uart",
      "title": "Chapter 11a: UART",
      "description": "UART connector signals, baud rate, and data format",
      "mimeType": "text/markdown"
    },
    {
      "uri": "lynx9_other_hardware",
      "title": "Chapter 12-13: Other Hardware Features",
      "description": "Multiply/Divide hardware, Parallel Port, Expansion Connector",
      "mimeType": "text/markdown"
    },
    {
      "uri": "lynx10_system_reset",
      "title": "Chapter 14-19: System Reset and Related Topics",
      "description": "System Reset/Power Up, Definitions, Variances, Exemptions, Common Errors, Savegame",
      "mimeType": "text/markdown"
    },
    {
      "uri": "lynx11_system_bus_interplay",
      "title": "Appendix 1: System Bus Interplay",
      "description": "System bus architecture and interactions",
      "mimeType": "text/markdown"
    },
    {
      "uri": "irq_interrupts_cpu_sleep",
      "title": "Appendix 2: Interrupts and CPU Sleep",
      "description": "Handy interrupts, CPU sleep mode, and debugging",
      "mimeType": "text/markdown"
    },
    {
      "uri": "hardware_addresses",
      "title": "Appendix 3: Hardware Addresses",
      "description": "Complete memory map and register documentation for Mikey and Suzy",
      "mimeType": "text/markdown"
    },
    {
      "uri": "sprite_engine",
      "title": "Appendix 4: Sprite Engine",
      "description": "Display creation, double-buffering, and sprite positioning",
      "mimeType": "text/markdown"
    }
  ]
}
